andrews_xsv-0.13.0.data/scripts/xsv
andrews_xsv-0.13.0.dist-info/METADATA
andrews_xsv-0.13.0.dist-info/WHEEL
andrews_xsv-0.13.0.dist-info/LICENSE-MIT
andrews_xsv-0.13.0.dist-info/top_level.txt
andrews_xsv-0.13.0.dist-info/RECORD
andrews_xsv-0.13.0.dist-info/COPYING
xsv/__init__.py
