Metadata-Version: 2.1
Name: andrews-xsv
Version: 0.13.0
Summary: A fast CSV command line toolkit written in Rust.
Home-page: https://github.com/sumitkanoje/xsv
Author: Andrew Gallant
Author-email: jamslam@gmail.com
Maintainer: Sumitkumar Kanoje
Maintainer-email: sumitkanoje@gmail.com
Classifier: Programming Language :: Python :: 3
Classifier: License :: OSI Approved :: MIT License
License-File: LICENSE-MIT
License-File: COPYING
